README.md
setup.cfg
setup.py
abuu/__init__.py
abuu.egg-info/PKG-INFO
abuu.egg-info/SOURCES.txt
abuu.egg-info/dependency_links.txt
abuu.egg-info/requires.txt
abuu.egg-info/top_level.txt
abuu/classes/__init__.py
abuu/classes/get_config_class.py
abuu/pandas/__init__.py
abuu/pandas/get_dataloader.py
abuu/pandas/make_dataframe.py
abuu/sklearn/__init__.py
abuu/sklearn/fit_estimators.py