Metadata-Version: 2.1
Name: abuu
Version: 0.0.1
Summary: ABUU - Another Bunch of Usefull Utils
Home-page: https://github.com/yashshah1/abuu
Author: Yash Shah
Author-email: yashshah1234@gmail.com
License: MIT
Platform: UNKNOWN
Classifier: Development Status :: 3 - Alpha
Classifier: License :: OSI Approved :: MIT License
Classifier: Programming Language :: Python :: 3
Classifier: Programming Language :: Python :: 3.7
